LICENSE
README.md
setup.cfg
setup.py
ashfaquecodes/__init__.py
ashfaquecodes/ashfaquecodes.py
ashfaquecodes.egg-info/PKG-INFO
ashfaquecodes.egg-info/SOURCES.txt
ashfaquecodes.egg-info/dependency_links.txt
ashfaquecodes.egg-info/requires.txt
ashfaquecodes.egg-info/top_level.txt