Metadata-Version: 2.1
Name: ashfaquecodes
Version: 0.8
Summary: Codes which can be used to increase productivity.
Home-page: https://github.com/ashfaque/ashfaquecodes
Download-URL: https://github.com/ashfaque/ashfaquecodes/archive/refs/tags/v_08.tar.gz
Author: Ashfaque Alam
Author-email: ashfaquealam496@yahoo.com
License: GNU GPLv3
Keywords: ASHFAQUE,ASHFAQUECODES,PRODUCTIVITY
Classifier: Development Status :: 5 - Production/Stable
Classifier: Intended Audience :: Developers
Classifier: Topic :: Software Development :: Build Tools
Classifier: Topic :: Software Development :: Libraries :: Python Modules
Classifier: License :: OSI Approved :: GNU General Public License (GPL)
Classifier: Operating System :: OS Independent
Classifier: Programming Language :: Python :: 3
Classifier: Programming Language :: Python :: 3 :: Only
Classifier: Programming Language :: Python :: 3.5
Classifier: Programming Language :: Python :: 3.6
Classifier: Programming Language :: Python :: 3.7
Classifier: Programming Language :: Python :: 3.8
Classifier: Programming Language :: Python :: 3.9
Classifier: Programming Language :: Python :: 3.10
Classifier: Programming Language :: Python :: 3.11
Classifier: Programming Language :: Python :: 3.12
License-File: LICENSE
Requires-Dist: colorama
